Workbook

Sheet Cover
B5: 180DC ESCP
B6: Financial Planning Model — Fall Semester 2026
B8: Prepared for: 180DC ESCP Finance Position — Recruitment Case Study
B9: Date: Fall 2026 | Version: 2.0 | Prepared by: David
B12: ORGANISATIONAL CONTEXT (Research-Based)
B13: Mission | C13: World's largest university-based consultancy for nonprofits and social enterprises (founded 2007, Sydney)
B14: ESCP Branch | C14: Active on 5 campuses: Paris, Berlin, London, Madrid, Turin. Serves European nonprofits and social enterprises.
B15: Client Profile | C15: Clients include Amnesty International, Rainforest Alliance, Les Restos du Coeur, Enercoop, Greenly, Fundacion Vicente Ferrer, UNHCR and similar.
B16: Revenue Model | C16: Primarily pro-bono or symbolic-fee. Revenue driven by corporate sponsorships, ESCP institutional support, and student membership fees.
B17: Project Fees | C17: Affordable/symbolic contribution (€300–800 per project) — NOT standard consulting rates. Clients are nonprofits with constrained budgets.
B18: Team Structure | C18: Presidency, Business Development, People & Org, Marketing, Operations, Consulting. ~5–6 consultants per project team with a Project Leader.
B19: Scale Benchmarks | C19: 80+ members; 8 projects/semester; 4-5 projects also cited for some comparable branches. Semester budget: ~€8,000–18,000 (European top school branch).
B22: WORKBOOK INDEX
B23: 1 | C23: Assumptions | D23: All model inputs. Blue = hardcoded input; Black = formula; Green = cross-sheet.
B24: 2 | C24: P&L Model | D24: Monthly profit & loss Sep–Dec 2026. Revenue, costs, net position and margins.
B25: 3 | C25: KPIs | D25: Eight KPIs with targets and RAG conditional formatting. Live-linked from P&L.
B26: 4 | C26: Sensitivity | D26: Two-variable table: projects × symbolic fee. Identifies break-even conditions.

Sheet Assumptions
A1: ASSUMPTIONS | 180DC ESCP Financial Model — Fall 2026
A2: Blue = hardcoded input | Black = formula | Green = cross-sheet reference | Assumptions reflect actual 180DC operations: pro-bono / symbolic-fee model
A3: Parameter | B3: Value | C3: Commentary / Source
A4: ORGANISATION — Confirmed from 180DC ESCP website & brief
A5: Total Members | B5: 85 | C5: Website shows ~30 named leadership + consultants; brief states 80+. Assumed 85.
A6: Active Consulting Members | B6: 52 | C6: ~5–6 consultants × 8 projects = 40–48 on projects; add Project Leaders and Head of Consulting dept.
A7: Executive / Admin Members | B7: =B5-B6 -> 33 | C7: Derived: total less active consultants. Covers Presidency, BD, P&O, Marketing, Operations.
A8: Number of Campuses | B8: 5 | C8: Paris, Berlin, London, Madrid, Turin — confirmed from ESCP website.
A9: Consultants per Project | B9: 6 | C9: Typical 180DC project team: 1 Project Leader + 5 Consultants.
A10: Semester Duration (months) | B10: 4 | C10: September through December 2026 inclusive.
A11: REVENUE — CONSULTING PROJECTS (Pro-Bono / Symbolic Contribution Model)
A12: Projects per Semester | B12: 8 | C12: Per brief. Consistent with top European 180DC branches.
A13: Symbolic Client Contribution (€) | B13: 500 | C13: 180DC serves nonprofits who cannot pay standard fees. Symbolic €300–800 is market norm for top-school EU branches.
A14: % of Projects with Contribution | B14: 0.75 | C14: Estimated 75% of clients make a symbolic contribution; remainder fully pro-bono.
A15: Project Revenue (€) | B15: =B12*B13*B14 -> 3000 | C15: Derived: projects × symbolic fee × contribution rate. Revenue is supplementary, not primary.
A16: REVENUE — CORPORATE SPONSORSHIPS (Primary Revenue Driver)
A17: Number of Corporate Sponsors | B17: 3 | C17: Top EU business school branches typically secure 2–4 sponsors per semester.
A18: Avg. Sponsorship Value (€) | B18: 4000 | C18: Mix of cash and in-kind. Range €2,000–8,000. Sponsors gain brand access to ESCP talent pipeline.
A19: Total Sponsorship Revenue (€) | B19: =B17*B18 -> 12000 | C19: Derived. Key driver: ESCP brand and multi-campus reach makes the branch attractive to corporate partners.
A20: REVENUE — INSTITUTIONAL SUPPORT & MEMBERSHIP
A21: ESCP University Grant / Support (€) | B21: 2000 | C21: ESCP student association budget allocation. Common practice at ESCP for recognised clubs.
A22: Membership Fee per Member (€) | B22: 20 | C22: Nominal semester fee. Kept low given pro-bono mission. €15–30 typical range.
A23: Gross Membership Revenue (€) | B23: =B5*B22 -> 1700 | C23: Derived: total members × membership fee. Collected upfront in September.
A24: Event / Workshop Ticket Revenue (€) | B24: 800 | C24: 2 events × ~20 external attendees × €20. Internal members attend free.
A25: Other Miscellaneous Revenue (€) | B25: 300 | C25: Grants, donations, merchandise. Conservative estimate.
A26: COSTS — EVENTS & ACTIVITIES
A27: Number of Events per Semester | B27: 4 | C27: 1 Kickoff, 1 Alumni/Networking, 1 Impact showcase, 1 Social. Standard 180DC branch calendar.
A28: Avg. Cost per Event (€) | B28: 600 | C28: Venue (often subsidised by ESCP), catering, materials. Low given campus facilities.
A29: Total Event Cost (€) | B29: =B27*B28 -> 2400 | C29: Derived.
A30: COSTS — OPERATIONS (Fixed Monthly)
A31: Marketing & Communications (€ / month) | B31: 120 | C31: Social media, printing, Canva. Lower than initially assumed given ESCP infrastructure support.
A32: Software & Digital Tools (€ / month) | B32: 60 | C32: Notion, Zoom Pro, survey tools. Some provided by ESCP.
A33: Admin & Miscellaneous (€ / month) | B33: 40 | C33: Postage, printing, banking fees.
A34: COSTS — PROJECT DELIVERY
A35: Project Delivery Costs (€ / project) | B35: 150 | C35: Materials, printing, client meetings. Low: students provide labour pro-bono.
A36: Travel & Client Meetings (€) | B36: 400 | C36: Cross-campus coordination and client site visits across 5 campuses.
A37: FINANCIAL POLICY
A38: Contingency Reserve (%) | B38: 0.08 | C38: 8% of operating costs held as buffer. Slightly higher than standard given multi-campus complexity.
A39: Target Net Margin (%) | B39: 0.05 | C39: Modest 5% target: organisation prioritises impact over financial surplus.
A40: Global Franchise Fee (%) | B40: 0 | C40: 180DC branches are autonomous; no royalty fee to global body confirmed. Set to 0 unless advised otherwise.

Sheet P&L Model
A1: P&L MODEL | 180DC ESCP — Fall Semester 2026
A2: Pro-bono / symbolic-fee model. Revenue driven by sponsorships and institutional support. All amounts in EUR (€).
A4: Line Item | B4: Full-Semester Basis | C4: September | D4: October | E4: November | F4: December | G4: FY Total
A5: I. REVENUE
A6: 1.1 Symbolic Project Contributions | B6: =Assumptions!B15 -> 3000 | C6: =Assumptions!B15*0.1 -> 300 | D6: =Assumptions!B15*0.25 -> 750 | E6: =Assumptions!B15*0.4 -> 1200 | F6: =Assumptions!B15*0.25 -> 750 | G6: =SUM(C6:F6) -> 3000
A7: 1.2 Corporate Sponsorships | B7: =Assumptions!B19 -> 12000 | C7: =Assumptions!B19*0.4 -> 4800 | D7: =Assumptions!B19*0 -> 0 | E7: =Assumptions!B19*0.4 -> 4800 | F7: =Assumptions!B19*0.2 -> 2400 | G7: =SUM(C7:F7) -> 12000
A8: 1.3 ESCP Institutional Grant / Support | B8: =Assumptions!B21 -> 2000 | C8: =Assumptions!B21*1 -> 2000 | D8: =Assumptions!B21*0 -> 0 | E8: =Assumptions!B21*0 -> 0 | F8: =Assumptions!B21*0 -> 0 | G8: =SUM(C8:F8) -> 2000
A9: 1.4 Membership Fees | B9: =Assumptions!B23 -> 1700 | C9: =Assumptions!B23*1 -> 1700 | D9: =Assumptions!B23*0 -> 0 | E9: =Assumptions!B23*0 -> 0 | F9: =Assumptions!B23*0 -> 0 | G9: =SUM(C9:F9) -> 1700
A10: 1.5 Event / Workshop Revenue | B10: =Assumptions!B24 -> 800 | C10: =Assumptions!B24*0 -> 0 | D10: =Assumptions!B24*0.5 -> 400 | E10: =Assumptions!B24*0.5 -> 400 | F10: =Assumptions!B24*0 -> 0 | G10: =SUM(C10:F10) -> 800
A11: 1.6 Other / Miscellaneous Revenue | B11: =Assumptions!B25 -> 300 | C11: =Assumptions!B25/4 -> 75 | D11: =Assumptions!B25/4 -> 75 | E11: =Assumptions!B25/4 -> 75 | F11: =Assumptions!B25/4 -> 75 | G11: =SUM(C11:F11) -> 300
A12: TOTAL REVENUE | B12: Semester aggregate | C12: =SUM(C6:C11) -> 8875 | D12: =SUM(D6:D11) -> 1225 | E12: =SUM(E6:E11) -> 6475 | F12: =SUM(F6:F11) -> 3225 | G12: =SUM(C12:F12) -> 19800
A14: II. COSTS
A15: 2.1 Events & Activities | B15: =Assumptions!B29 -> 2400 | C15: =Assumptions!B29*0.25 -> 600 | D15: =Assumptions!B29*0.3 -> 720 | E15: =Assumptions!B29*0.3 -> 720 | F15: =Assumptions!B29*0.15 -> 360 | G15: =SUM(C15:F15) -> 2400
A16: 2.2 Project Delivery Costs | B16: Per project (materials, meetings) | C16: =Assumptions!B35*Assumptions!B12*0.1 -> 120 | D16: =Assumptions!B35*Assumptions!B12*0.25 -> 300 | E16: =Assumptions!B35*Assumptions!B12*0.4 -> 480 | F16: =Assumptions!B35*Assumptions!B12*0.25 -> 300 | G16: =SUM(C16:F16) -> 1200
A17: 2.3 Travel & Client Meetings | B17: Multi-campus coordination | C17: =Assumptions!B36/4 -> 100 | D17: =Assumptions!B36/4 -> 100 | E17: =Assumptions!B36/4 -> 100 | F17: =Assumptions!B36/4 -> 100 | G17: =SUM(C17:F17) -> 400
A18: 2.4 Marketing & Communications | B18: Fixed monthly cost | C18: =Assumptions!B31 -> 120 | D18: =Assumptions!B31 -> 120 | E18: =Assumptions!B31 -> 120 | F18: =Assumptions!B31 -> 120 | G18: =SUM(C18:F18) -> 480
A19: 2.5 Software & Digital Tools | B19: Fixed monthly cost | C19: =Assumptions!B32 -> 60 | D19: =Assumptions!B32 -> 60 | E19: =Assumptions!B32 -> 60 | F19: =Assumptions!B32 -> 60 | G19: =SUM(C19:F19) -> 240
A20: 2.6 Admin & Miscellaneous | B20: Fixed monthly cost | C20: =Assumptions!B33 -> 40 | D20: =Assumptions!B33 -> 40 | E20: =Assumptions!B33 -> 40 | F20: =Assumptions!B33 -> 40 | G20: =SUM(C20:F20) -> 160
A21: 2.7 Contingency Reserve (8%) | B21: 8% of operating costs | C21: =SUM(C15:C20)*Assumptions!B38 -> 83.2 | D21: =SUM(D15:D20)*Assumptions!B38 -> 107.2 | E21: =SUM(E15:E20)*Assumptions!B38 -> 121.6 | F21: =SUM(F15:F20)*Assumptions!B38 -> 78.4 | G21: =SUM(C21:F21) -> 390.4
A22: TOTAL COSTS | B22: Semester aggregate | C22: =SUM(C15:C21) -> 1123.2 | D22: =SUM(D15:D21) -> 1447.2 | E22: =SUM(E15:E21) -> 1641.6 | F22: =SUM(F15:F21) -> 1058.4 | G22: =SUM(C22:F22) -> 5270.4
A24: III. NET FINANCIAL POSITION
A25: Gross Surplus / (Deficit) | B25: Revenue – Costs | C25: =C12-C22 -> 7751.8 | D25: =D12-D22 -> -222.2 | E25: =E12-E22 -> 4833.4 | F25: =F12-F22 -> 2166.6 | G25: =G12-G22 -> 14529.6
A26: Cumulative Net Position | B26: Running total | C26: =C25 -> 7751.8 | D26: =C26+D25 -> 7529.6 | E26: =D26+E25 -> 12363 | F26: =E26+F25 -> 14529.6 | G26: =F26 -> 14529.6
A27: Net Margin (%) | B27: Surplus / Revenue | C27: =IFERROR(C25/C12,0) -> 0.87344225 | D27: =IFERROR(D25/D12,0) -> -0.18138776 | E27: =IFERROR(E25/E12,0) -> 0.74647104 | F27: =IFERROR(F25/F12,0) -> 0.67181395 | G27: =IFERROR(G25/G12,0) -> 0.73381818
A28: Cost-to-Revenue Ratio (%) | B28: Costs / Revenue | C28: =IFERROR(C22/C12,0) -> 0.12655775 | D28: =IFERROR(D22/D12,0) -> 1.1813878 | E28: =IFERROR(E22/E12,0) -> 0.25352896 | F28: =IFERROR(F22/F12,0) -> 0.32818605 | G28: =IFERROR(G22/G12,0) -> 0.26618182

Sheet KPIs
B1: FINANCIAL KPI TRACKER | 180DC ESCP — Fall 2026
B2: 8 KPIs with targets calibrated to 180DC pro-bono model. RAG via conditional formatting. Live-linked.
B4: # | C4: KPI | D4: Value | E4: Definition | F4: Target | G4: Status
B5: 1 | C5: Sponsorship Coverage Ratio (%) | D5: =IFERROR('P&L Model'!G7/'P&L Model'!G22,0) -> 2.276867 | E5: Sponsorship revenue as % of total costs — primary sustainability indicator for a pro-bono branch | F5: ≥ 60% | G5: =IFERROR(IF(D5>=0.6,"On Target","Below Target"),"-") -> On Target
B6: 2 | C6: Cost per Member (€) | D6: =IFERROR('P&L Model'!G22/Assumptions!B5,0) -> 62.004706 | E6: Total semester costs divided by total members — efficiency of resource deployment | F6: ≤ €100 | G6: =IFERROR(IF(D6<=100,"On Target","Above Target"),"-") -> On Target
B7: 3 | C7: Net Surplus / (Deficit) (€) | D7: ='P&L Model'!G25 -> 14529.6 | E7: Total revenue minus total costs. Modest surplus reinvested in branch development. | F7: > €0 | G7: =IFERROR(IF(D7>0,"Surplus","Deficit"),"-") -> Surplus
B8: 4 | C8: Net Margin (%) | D8: =IFERROR('P&L Model'!G25/'P&L Model'!G12,0) -> 0.73381818 | E8: Net surplus as % of revenue. Target kept modest — organisation prioritises social impact. | F8: ≥ 5% | G8: =IFERROR(IF(D8>=Assumptions!B39,"On Target","Below Target"),"-") -> On Target
B9: 5 | C9: Revenue per Project (€) | D9: =IFERROR('P&L Model'!G12/Assumptions!B12,0) -> 2475 | E9: Average total revenue allocated per consulting project delivered — capacity planning metric | F9: ≥ €1,200 | G9: =IFERROR(IF(D9>=1200,"On Target","Below Target"),"-") -> On Target
B10: 6 | C10: Institutional & Sponsorship as % of Revenue | D10: =IFERROR(('P&L Model'!G7+'P&L Model'!G8)/'P&L Model'!G12,0) -> 0.70707071 | E10: Combined sponsorship + institutional grant share of total revenue — funding structure health | F10: ≥ 50% | G10: =IFERROR(IF(D10>=0.5,"Healthy","Review Mix"),"-") -> Healthy
B11: 7 | C11: Events Cost as % of Total Costs | D11: =IFERROR('P&L Model'!G15/'P&L Model'!G22,0) -> 0.45537341 | E11: Events spend divided by total costs — checks spend concentration in non-core activity | F11: ≤ 35% | G11: =IFERROR(IF(D11<=0.35,"On Target","Overspend"),"-") -> Overspend
B12: 8 | C12: Revenue per Active Member (€) | D12: =IFERROR('P&L Model'!G12/Assumptions!B6,0) -> 380.76923 | E12: Total revenue divided by active consulting members — fundraising & business development productivity | F12: ≥ €200 | G12: =IFERROR(IF(D12>=200,"On Target","Below Target"),"-") -> On Target

Sheet Sensitivity
B1: SENSITIVITY ANALYSIS | Net Surplus (€) — Projects × Symbolic Fee
B2: Rows = number of projects; Columns = symbolic client contribution per project (€). Sponsorships, grants and fixed costs held constant at base assumptions. Shaded cell = base case. Green = surplus; Red = deficit.
C4: Symbolic Client Contribution (€ per project)
C5: 0 | D5: 300 | E5: 500 | F5: 700 | G5: 1000
B6: 5 | C6: =(5*0*Assumptions!B14+Assumptions!B19+Assumptions!B21+Assumptions!B23+Assumptions!B24+Assumptions!B25)-Assumptions!B29+Assumptions!B35*5+Assumptions!B36+(Assumptions!B31+Assumptions!B32+Assumptions!B33)*4*(1+Assumptions!B38) -> 16500.4 | D6: =(5*300*Assumptions!B14+Assumptions!B19+Assumptions!B21+Assumptions!B23+Assumptions!B24+Assumptions!B25)-Assumptions!B29+Assumptions!B35*5+Assumptions!B36+(Assumptions!B31+Assumptions!B32+Assumptions!B33)*4*(1+Assumptions!B38) -> 17625.4 | E6: =(5*500*Assumptions!B14+Assumptions!B19+Assumptions!B21+Assumptions!B23+Assumptions!B24+Assumptions!B25)-Assumptions!B29+Assumptions!B35*5+Assumptions!B36+(Assumptions!B31+Assumptions!B32+Assumptions!B33)*4*(1+Assumptions!B38) -> 18375.4 | F6: =(5*700*Assumptions!B14+Assumptions!B19+Assumptions!B21+Assumptions!B23+Assumptions!B24+Assumptions!B25)-Assumptions!B29+Assumptions!B35*5+Assumptions!B36+(Assumptions!B31+Assumptions!B32+Assumptions!B33)*4*(1+Assumptions!B38) -> 19125.4 | G6: =(5*1000*Assumptions!B14+Assumptions!B19+Assumptions!B21+Assumptions!B23+Assumptions!B24+Assumptions!B25)-Assumptions!B29+Assumptions!B35*5+Assumptions!B36+(Assumptions!B31+Assumptions!B32+Assumptions!B33)*4*(1+Assumptions!B38) -> 20250.4
B7: 6 | C7: =(6*0*Assumptions!B14+Assumptions!B19+Assumptions!B21+Assumptions!B23+Assumptions!B24+Assumptions!B25)-Assumptions!B29+Assumptions!B35*6+Assumptions!B36+(Assumptions!B31+Assumptions!B32+Assumptions!B33)*4*(1+Assumptions!B38) -> 16650.4 | D7: =(6*300*Assumptions!B14+Assumptions!B19+Assumptions!B21+Assumptions!B23+Assumptions!B24+Assumptions!B25)-Assumptions!B29+Assumptions!B35*6+Assumptions!B36+(Assumptions!B31+Assumptions!B32+Assumptions!B33)*4*(1+Assumptions!B38) -> 18000.4 | E7: =(6*500*Assumptions!B14+Assumptions!B19+Assumptions!B21+Assumptions!B23+Assumptions!B24+Assumptions!B25)-Assumptions!B29+Assumptions!B35*6+Assumptions!B36+(Assumptions!B31+Assumptions!B32+Assumptions!B33)*4*(1+Assumptions!B38) -> 18900.4 | F7: =(6*700*Assumptions!B14+Assumptions!B19+Assumptions!B21+Assumptions!B23+Assumptions!B24+Assumptions!B25)-Assumptions!B29+Assumptions!B35*6+Assumptions!B36+(Assumptions!B31+Assumptions!B32+Assumptions!B33)*4*(1+Assumptions!B38) -> 19800.4 | G7: =(6*1000*Assumptions!B14+Assumptions!B19+Assumptions!B21+Assumptions!B23+Assumptions!B24+Assumptions!B25)-Assumptions!B29+Assumptions!B35*6+Assumptions!B36+(Assumptions!B31+Assumptions!B32+Assumptions!B33)*4*(1+Assumptions!B38) -> 21150.4
B8: 7 | C8: =(7*0*Assumptions!B14+Assumptions!B19+Assumptions!B21+Assumptions!B23+Assumptions!B24+Assumptions!B25)-Assumptions!B29+Assumptions!B35*7+Assumptions!B36+(Assumptions!B31+Assumptions!B32+Assumptions!B33)*4*(1+Assumptions!B38) -> 16800.4 | D8: =(7*300*Assumptions!B14+Assumptions!B19+Assumptions!B21+Assumptions!B23+Assumptions!B24+Assumptions!B25)-Assumptions!B29+Assumptions!B35*7+Assumptions!B36+(Assumptions!B31+Assumptions!B32+Assumptions!B33)*4*(1+Assumptions!B38) -> 18375.4 | E8: =(7*500*Assumptions!B14+Assumptions!B19+Assumptions!B21+Assumptions!B23+Assumptions!B24+Assumptions!B25)-Assumptions!B29+Assumptions!B35*7+Assumptions!B36+(Assumptions!B31+Assumptions!B32+Assumptions!B33)*4*(1+Assumptions!B38) -> 19425.4 | F8: =(7*700*Assumptions!B14+Assumptions!B19+Assumptions!B21+Assumptions!B23+Assumptions!B24+Assumptions!B25)-Assumptions!B29+Assumptions!B35*7+Assumptions!B36+(Assumptions!B31+Assumptions!B32+Assumptions!B33)*4*(1+Assumptions!B38) -> 20475.4 | G8: =(7*1000*Assumptions!B14+Assumptions!B19+Assumptions!B21+Assumptions!B23+Assumptions!B24+Assumptions!B25)-Assumptions!B29+Assumptions!B35*7+Assumptions!B36+(Assumptions!B31+Assumptions!B32+Assumptions!B33)*4*(1+Assumptions!B38) -> 22050.4
B9: 8 | C9: =(8*0*Assumptions!B14+Assumptions!B19+Assumptions!B21+Assumptions!B23+Assumptions!B24+Assumptions!B25)-Assumptions!B29+Assumptions!B35*8+Assumptions!B36+(Assumptions!B31+Assumptions!B32+Assumptions!B33)*4*(1+Assumptions!B38) -> 16950.4 | D9: =(8*300*Assumptions!B14+Assumptions!B19+Assumptions!B21+Assumptions!B23+Assumptions!B24+Assumptions!B25)-Assumptions!B29+Assumptions!B35*8+Assumptions!B36+(Assumptions!B31+Assumptions!B32+Assumptions!B33)*4*(1+Assumptions!B38) -> 18750.4 | E9: =(8*500*Assumptions!B14+Assumptions!B19+Assumptions!B21+Assumptions!B23+Assumptions!B24+Assumptions!B25)-Assumptions!B29+Assumptions!B35*8+Assumptions!B36+(Assumptions!B31+Assumptions!B32+Assumptions!B33)*4*(1+Assumptions!B38) -> 19950.4 | F9: =(8*700*Assumptions!B14+Assumptions!B19+Assumptions!B21+Assumptions!B23+Assumptions!B24+Assumptions!B25)-Assumptions!B29+Assumptions!B35*8+Assumptions!B36+(Assumptions!B31+Assumptions!B32+Assumptions!B33)*4*(1+Assumptions!B38) -> 21150.4 | G9: =(8*1000*Assumptions!B14+Assumptions!B19+Assumptions!B21+Assumptions!B23+Assumptions!B24+Assumptions!B25)-Assumptions!B29+Assumptions!B35*8+Assumptions!B36+(Assumptions!B31+Assumptions!B32+Assumptions!B33)*4*(1+Assumptions!B38) -> 22950.4
B10: 9 | C10: =(9*0*Assumptions!B14+Assumptions!B19+Assumptions!B21+Assumptions!B23+Assumptions!B24+Assumptions!B25)-Assumptions!B29+Assumptions!B35*9+Assumptions!B36+(Assumptions!B31+Assumptions!B32+Assumptions!B33)*4*(1+Assumptions!B38) -> 17100.4 | D10: =(9*300*Assumptions!B14+Assumptions!B19+Assumptions!B21+Assumptions!B23+Assumptions!B24+Assumptions!B25)-Assumptions!B29+Assumptions!B35*9+Assumptions!B36+(Assumptions!B31+Assumptions!B32+Assumptions!B33)*4*(1+Assumptions!B38) -> 19125.4 | E10: =(9*500*Assumptions!B14+Assumptions!B19+Assumptions!B21+Assumptions!B23+Assumptions!B24+Assumptions!B25)-Assumptions!B29+Assumptions!B35*9+Assumptions!B36+(Assumptions!B31+Assumptions!B32+Assumptions!B33)*4*(1+Assumptions!B38) -> 20475.4 | F10: =(9*700*Assumptions!B14+Assumptions!B19+Assumptions!B21+Assumptions!B23+Assumptions!B24+Assumptions!B25)-Assumptions!B29+Assumptions!B35*9+Assumptions!B36+(Assumptions!B31+Assumptions!B32+Assumptions!B33)*4*(1+Assumptions!B38) -> 21825.4 | G10: =(9*1000*Assumptions!B14+Assumptions!B19+Assumptions!B21+Assumptions!B23+Assumptions!B24+Assumptions!B25)-Assumptions!B29+Assumptions!B35*9+Assumptions!B36+(Assumptions!B31+Assumptions!B32+Assumptions!B33)*4*(1+Assumptions!B38) -> 23850.4
B11: 10 | C11: =(10*0*Assumptions!B14+Assumptions!B19+Assumptions!B21+Assumptions!B23+Assumptions!B24+Assumptions!B25)-Assumptions!B29+Assumptions!B35*10+Assumptions!B36+(Assumptions!B31+Assumptions!B32+Assumptions!B33)*4*(1+Assumptions!B38) -> 17250.4 | D11: =(10*300*Assumptions!B14+Assumptions!B19+Assumptions!B21+Assumptions!B23+Assumptions!B24+Assumptions!B25)-Assumptions!B29+Assumptions!B35*10+Assumptions!B36+(Assumptions!B31+Assumptions!B32+Assumptions!B33)*4*(1+Assumptions!B38) -> 19500.4 | E11: =(10*500*Assumptions!B14+Assumptions!B19+Assumptions!B21+Assumptions!B23+Assumptions!B24+Assumptions!B25)-Assumptions!B29+Assumptions!B35*10+Assumptions!B36+(Assumptions!B31+Assumptions!B32+Assumptions!B33)*4*(1+Assumptions!B38) -> 21000.4 | F11: =(10*700*Assumptions!B14+Assumptions!B19+Assumptions!B21+Assumptions!B23+Assumptions!B24+Assumptions!B25)-Assumptions!B29+Assumptions!B35*10+Assumptions!B36+(Assumptions!B31+Assumptions!B32+Assumptions!B33)*4*(1+Assumptions!B38) -> 22500.4 | G11: =(10*1000*Assumptions!B14+Assumptions!B19+Assumptions!B21+Assumptions!B23+Assumptions!B24+Assumptions!B25)-Assumptions!B29+Assumptions!B35*10+Assumptions!B36+(Assumptions!B31+Assumptions!B32+Assumptions!B33)*4*(1+Assumptions!B38) -> 24750.4
C13: Shaded = base case (8 projects, €500 symbolic fee). Column at €0 = fully pro-bono scenario. Break-even identified where cell turns green.

Sheet Project Tracker
B1: PROJECT TRACKER | 180DC ESCP — Fall Semester 2026
B2: Live register of all consulting projects. Update Status and Actual Hours weekly. Fee columns feed back to the P&L Model for variance tracking.
B4: # | C4: Client Name | D4: Sector / Impact Area | E4: Project Leader | F4: Consultants (names) | G4: Team | H4: Start | I4: End | J4: Status | K4: Hrs Budget | L4: Hrs Actual | M4: Completion % | N4: Fee (€) | O4: Inv. | P4: Received (€) | Q4: Outstanding (€) | R4: Key Deliverable / Notes
B5: 1 | C5: Greenly | D5: Sustainability & Climate Tech | E5: Carl-Vincent von Glenck | F5: L. Manzoni, A. Chandel, M. Bozzoli, R. Deren, U. Jargalsaikhan | G5: 6 | H5: 01-Sep-26 | I5: 31-Oct-26 | J5: Completed | K5: 180 | L5: 172 | M5: =IFERROR(L5/K5,0) -> 0.95555556 | N5: 500 | O5: Yes | P5: 500 | Q5: =IF(O5="Yes",N5-P5,0) -> 0 | R5: Carbon footprint methodology benchmarking for SaaS clients
B6: 2 | C6: Amnesty International | D6: Social Welfare & Human Rights | E6: Daniele Ovazza | F6: I. Desmaretz, L. Sri, K. Baskaran, A. Pangil Mohan, N. Rathor | G6: 6 | H6: 01-Sep-26 | I6: 15-Nov-26 | J6: Under Review | K6: 200 | L6: 145 | M6: =IFERROR(L6/K6,0) -> 0.725 | N6: 500 | O6: Yes | P6: 500 | Q6: =IF(O6="Yes",N6-P6,0) -> 0 | R6: Volunteer engagement strategy & donor retention model
B7: 3 | C7: Rainforest Alliance | D7: Sustainability & Climate Tech | E7: Kyungwon Lee | F7: S. Ravichandran, V. von Falkenhausen, A. Egle, D. Ibrahim | G7: 5 | H7: 15-Sep-26 | I7: 30-Nov-26 | J7: Active | K7: 180 | L7: 98 | M7: =IFERROR(L7/K7,0) -> 0.54444444 | N7: 500 | O7: Yes | P7: 0 | Q7: =IF(O7="Yes",N7-P7,0) -> 500 | R7: Supply chain transparency framework for certified producers
B8: 4 | C8: Enercoop | D8: Sustainability & Climate Tech | E8: Lukas Brehm | F8: A. Skrzynska, S. Kanwischer, M. Luty, X. Yuan | G8: 5 | H8: 01-Oct-26 | I8: 20-Dec-26 | J8: Active | K8: 200 | L8: 60 | M8: =IFERROR(L8/K8,0) -> 0.3 | N8: 500 | O8: No | P8: 0 | Q8: =IF(O8="Yes",N8-P8,0) -> 0 | R8: Go-to-market strategy for cooperative energy membership expansion
B9: 5 | C9: Fundacion Vicente Ferrer | D9: Social Welfare & Support | E9: Giulia Renga | F9: A. Noronha, D. Ovazza, A. Vasi Shaikh, K. Lee | G9: 5 | H9: 15-Sep-26 | I9: 30-Nov-26 | J9: Active | K9: 160 | L9: 88 | M9: =IFERROR(L9/K9,0) -> 0.55 | N9: 500 | O9: Yes | P9: 500 | Q9: =IF(O9="Yes",N9-P9,0) -> 0 | R9: Impact measurement framework & donor communication strategy
B10: 6 | C10: EASPD | D10: Disability & Inclusion | E10: Alonso Gonzalez | F10: L. Brehm, M. Fantoni, S. Deriya, J. Kaur | G10: 5 | H10: 01-Oct-26 | I10: 15-Dec-26 | J10: Active | K10: 180 | L10: 52 | M10: =IFERROR(L10/K10,0) -> 0.28888889 | N10: 0 | O10: No | P10: 0 | Q10: =IF(O10="Yes",N10-P10,0) -> 0 | R10: European policy advocacy strategy (pro-bono — no fee)
B11: 7 | C11: Impact Hub Berlin | D11: Innovation Ecosystems | E11: Shreyansh Deriya | F11: D. Nidhi, A. Michel, M. Dolz, M. Luty | G11: 5 | H11: 15-Oct-26 | I11: 20-Dec-26 | J11: Scoping | K11: 160 | L11: 12 | M11: =IFERROR(L11/K11,0) -> 0.075 | N11: 500 | O11: No | P11: 0 | Q11: =IF(O11="Yes",N11-P11,0) -> 0 | R11: Community scaling model & partnership framework
B12: 8 | C12: SEO London | D12: Education & EdTech | E12: Marianne Luty | F12: S. Kanwischer, A. Skrzynska, A. Egle, N. Rathor | G12: 5 | H12: 01-Nov-26 | I12: 31-Dec-26 | J12: Scoping | K12: 160 | L12: 8 | M12: =IFERROR(L12/K12,0) -> 0.05 | N12: 0 | O12: No | P12: 0 | Q12: =IF(O12="Yes",N12-P12,0) -> 0 | R12: Talent pipeline strategy for underrepresented students (pro-bono)
C13: TOTALS | K13: =SUM(K5:K12) -> 1420 | L13: =SUM(L5:L12) -> 635 | M13: =IFERROR(L13/K13,0) -> 0.4471831 | N13: =SUM(N5:N12) -> 3000 | P13: =SUM(P5:P12) -> 1500 | Q13: =SUM(Q5:Q12) -> 500
B15: Note: Outstanding (€) auto-calculates only for invoiced projects. Pro-bono projects (EASPD, SEO London) show €0 fee by design. Update Hrs Actual weekly; Status via dropdown.

Sheet Variance
B1: SEMESTER VARIANCE | Spring 2026 (Est.) vs. Fall 2026 (Budget)
B2: Spring 2026 figures are management estimates based on prior-semester patterns. Positive variance = improvement. Update Spring column with actuals once available.
B4: Line Item | C4: Spring 2026 (Estimated) | D4: Fall 2026 (Budget) | E4: Variance (€) | F4: Variance (%)
B5: I. REVENUE
B6: 1.1 Symbolic Project Contributions | C6: 2200 | D6: ='P&L Model'!G6 -> 3000 | E6: =D6-C6 -> 800 | F6: =IFERROR((D6-C6)/ABS(C6),0) -> 0.36363636
B7: 1.2 Corporate Sponsorships | C7: 7000 | D7: ='P&L Model'!G7 -> 12000 | E7: =D7-C7 -> 5000 | F7: =IFERROR((D7-C7)/ABS(C7),0) -> 0.71428571
B8: 1.3 ESCP Institutional Grant | C8: 2000 | D8: ='P&L Model'!G8 -> 2000 | E8: =D8-C8 -> 0 | F8: =IFERROR((D8-C8)/ABS(C8),0) -> 0
B9: 1.4 Membership Fees | C9: 1640 | D9: ='P&L Model'!G9 -> 1700 | E9: =D9-C9 -> 60 | F9: =IFERROR((D9-C9)/ABS(C9),0) -> 0.036585366
B10: 1.5 Event / Workshop Revenue | C10: 700 | D10: ='P&L Model'!G10 -> 800 | E10: =D10-C10 -> 100 | F10: =IFERROR((D10-C10)/ABS(C10),0) -> 0.14285714
B11: 1.6 Other / Miscellaneous | C11: 250 | D11: ='P&L Model'!G11 -> 300 | E11: =D11-C11 -> 50 | F11: =IFERROR((D11-C11)/ABS(C11),0) -> 0.2
B12: TOTAL REVENUE | C12: 13790 | D12: ='P&L Model'!G12 -> 19800 | E12: =D12-C12 -> 6010 | F12: =IFERROR((D12-C12)/ABS(C12),0) -> 0.43582306
B13: II. COSTS
B14: 2.1 Events & Activities | C14: 1650 | D14: ='P&L Model'!G15 -> 2400 | E14: =D14-C14 -> 750 | F14: =IFERROR((D14-C14)/ABS(C14),0) -> 0.45454545
B15: 2.2 Project Delivery Costs | C15: 1050 | D15: ='P&L Model'!G16 -> 1200 | E15: =D15-C15 -> 150 | F15: =IFERROR((D15-C15)/ABS(C15),0) -> 0.14285714
B16: 2.3 Travel & Client Meetings | C16: 350 | D16: ='P&L Model'!G17 -> 400 | E16: =D16-C16 -> 50 | F16: =IFERROR((D16-C16)/ABS(C16),0) -> 0.14285714
B17: 2.4 Marketing & Communications | C17: 480 | D17: ='P&L Model'!G18 -> 480 | E17: =D17-C17 -> 0 | F17: =IFERROR((D17-C17)/ABS(C17),0) -> 0
B18: 2.5 Software & Digital Tools | C18: 240 | D18: ='P&L Model'!G19 -> 240 | E18: =D18-C18 -> 0 | F18: =IFERROR((D18-C18)/ABS(C18),0) -> 0
B19: 2.6 Admin & Miscellaneous | C19: 160 | D19: ='P&L Model'!G20 -> 160 | E19: =D19-C19 -> 0 | F19: =IFERROR((D19-C19)/ABS(C19),0) -> 0
B20: 2.7 Contingency Reserve | C20: 314 | D20: ='P&L Model'!G21 -> 390.4 | E20: =D20-C20 -> 76.4 | F20: =IFERROR((D20-C20)/ABS(C20),0) -> 0.2433121
B21: TOTAL COSTS | C21: 4244 | D21: ='P&L Model'!G22 -> 5270.4 | E21: =D21-C21 -> 1026.4 | F21: =IFERROR((D21-C21)/ABS(C21),0) -> 0.24184731
B22: III. NET POSITION
B23: Gross Surplus / (Deficit) | C23: 9546 | D23: ='P&L Model'!G25 -> 14529.6 | E23: =D23-C23 -> 4983.6 | F23: =IFERROR((D23-C23)/ABS(C23),0) -> 0.5220616
B24: Net Margin (%) | C24: 0.69224075 | D24: =IFERROR('P&L Model'!G25/'P&L Model'!G12,0) -> 0.73381818 | E24: =D24-C24 -> 0.041577428 | F24: =IFERROR((D24-C24)/ABS(C24),0) -> 0.060062092
B26: Spring 2026 estimates: 7 projects, 2 sponsors, 3 events. Fall 2026 budget: 8 projects, 3 sponsors, 4 events. Fill blue cells with Spring actuals once semester closes.

Sheet Scenarios
B1: SCENARIO PLANNING | Conservative — Base — Optimistic
B2: Three full-model scenarios for executive decision-making. Base = current budget. All assumptions hardcoded per scenario for auditability.
B4: Parameter | C4: Conservative | D4: Base (Budget) | E4: Optimistic | F4: Upside vs. Base
B5: REVENUE ASSUMPTIONS
B6: Projects per Semester | C6: 6 | D6: 8 | E6: 10 | F6: =E6-D6 -> 2
B7: Symbolic Fee per Project (€) | C7: 300 | D7: 500 | E7: 700 | F7: =E7-D7 -> 200
B8: % Projects with Contribution | C8: 0.6 | D8: 0.75 | E8: 0.9 | F8: =E8-D8 -> 0.15
B9: Number of Sponsors | C9: 2 | D9: 3 | E9: 4 | F9: =E9-D9 -> 1
B10: Avg. Sponsor Value (€) | C10: 3000 | D10: 4000 | E10: 5500 | F10: =E10-D10 -> 1500
B11: ESCP Grant (€) | C11: 1500 | D11: 2000 | E11: 2500 | F11: =E11-D11 -> 500
B12: Total Members | C12: 75 | D12: 85 | E12: 95 | F12: =E12-D12 -> 10
B13: Membership Fee (€) | C13: 15 | D13: 20 | E13: 25 | F13: =E13-D13 -> 5
B14: COST ASSUMPTIONS
B15: Number of Events | C15: 3 | D15: 4 | E15: 5 | F15: =E15-D15 -> 1
B16: Avg. Cost per Event (€) | C16: 500 | D16: 600 | E16: 750 | F16: =E16-D16 -> 150
B17: Project Delivery Cost / Project (€) | C17: 100 | D17: 150 | E17: 200 | F17: =E17-D17 -> 50
B18: Monthly Operating Costs (€) | C18: 180 | D18: 220 | E18: 280 | F18: =E18-D18 -> 60
B19: DERIVED FINANCIAL OUTCOMES
B20: Total Revenue (€) | C20: 10705 | D20: 19800 | E20: 34575 | F20: =E20-D20 -> 14775
B21: Total Costs (€) | C21: 3694 | D21: 5270 | E21: 7844 | F21: =E21-D21 -> 2574
B22: Gross Surplus / (Deficit) (€) | C22: 7011 | D22: 14530 | E22: 26731 | F22: =E22-D22 -> 12201
B23: Net Margin (%) | C23: 0.655 | D23: 0.734 | E23: 0.773 | F23: =E23-D23 -> 0.039
B24: Revenue per Project (€) | C24: 1784 | D24: 2475 | E24: 3458 | F24: =E24-D24 -> 983
B25: Cost per Member (€) | C25: 49 | D25: 62 | E25: 83 | F25: =E25-D25 -> 21
B26: Rev. per Active Member (€) | C26: 206 | D26: 381 | E26: 693 | F26: =E26-D26 -> 312
B29: All scenario figures are independently calculated for full auditability. Base column matches P&L Model. Conservative = 1 fewer project, 1 fewer sponsor, reduced fees. Optimistic = 2 extra projects, 1 extra sponsor, 40% higher fees.

Sheet Campus Split
B1: CAMPUS BUDGET SPLIT | 180DC ESCP — Fall Semester 2026
B2: Consolidated budget allocated across 5 campuses based on member headcount. Adjust allocation weights (blue cells) to reflect campus-specific activity levels.
B4: Budget Line | C4: Paris | D4: Berlin | E4: London | F4: Madrid | G4: Turin | H4: TOTAL | I4: Verify vs. P&L
B5: Member Headcount | C5: 30 | D5: 22 | E5: 18 | F5: 10 | G5: 5 | H5: =SUM(C5:G5) -> 85 | I5: 85 total members
B6: Allocation Weight (%) | C6: =C5/H5 -> 0.35294118 | D6: =D5/H5 -> 0.25882353 | E6: =E5/H5 -> 0.21176471 | F6: =F5/H5 -> 0.11764706 | G6: =G5/H5 -> 0.058823529 | H6: =SUM(C6:G6) -> 1 | I6: Must sum to 100%
B8: I. REVENUE ALLOCATION
B9: 1.1 Symbolic Project Contributions | C9: ='P&L Model'!G6*C6 -> 1058.8235 | D9: ='P&L Model'!G6*D6 -> 776.47059 | E9: ='P&L Model'!G6*E6 -> 635.29412 | F9: ='P&L Model'!G6*F6 -> 352.94118 | G9: ='P&L Model'!G6*G6 -> 176.47059 | H9: =SUM(C9:G9) -> 3000 | I9: =H9-'P&L Model'!G6 -> 0
B10: 1.2 Corporate Sponsorships | C10: ='P&L Model'!G7*C6 -> 4235.2941 | D10: ='P&L Model'!G7*D6 -> 3105.8824 | E10: ='P&L Model'!G7*E6 -> 2541.1765 | F10: ='P&L Model'!G7*F6 -> 1411.7647 | G10: ='P&L Model'!G7*G6 -> 705.88235 | H10: =SUM(C10:G10) -> 12000 | I10: =H10-'P&L Model'!G7 -> 0
B11: 1.3 ESCP Institutional Grant | C11: ='P&L Model'!G8*C6 -> 705.88235 | D11: ='P&L Model'!G8*D6 -> 517.64706 | E11: ='P&L Model'!G8*E6 -> 423.52941 | F11: ='P&L Model'!G8*F6 -> 235.29412 | G11: ='P&L Model'!G8*G6 -> 117.64706 | H11: =SUM(C11:G11) -> 2000 | I11: =H11-'P&L Model'!G8 -> 0
B12: 1.4 Membership Fees | C12: ='P&L Model'!G9*C6 -> 600 | D12: ='P&L Model'!G9*D6 -> 440 | E12: ='P&L Model'!G9*E6 -> 360 | F12: ='P&L Model'!G9*F6 -> 200 | G12: ='P&L Model'!G9*G6 -> 100 | H12: =SUM(C12:G12) -> 1700 | I12: =H12-'P&L Model'!G9 -> 0
B13: 1.5 Event / Workshop Revenue | C13: ='P&L Model'!G10*C6 -> 282.35294 | D13: ='P&L Model'!G10*D6 -> 207.05882 | E13: ='P&L Model'!G10*E6 -> 169.41176 | F13: ='P&L Model'!G10*F6 -> 94.117647 | G13: ='P&L Model'!G10*G6 -> 47.058824 | H13: =SUM(C13:G13) -> 800 | I13: =H13-'P&L Model'!G10 -> 0
B14: 1.6 Other Revenue | C14: ='P&L Model'!G11*C6 -> 105.88235 | D14: ='P&L Model'!G11*D6 -> 77.647059 | E14: ='P&L Model'!G11*E6 -> 63.529412 | F14: ='P&L Model'!G11*F6 -> 35.294118 | G14: ='P&L Model'!G11*G6 -> 17.647059 | H14: =SUM(C14:G14) -> 300 | I14: =H14-'P&L Model'!G11 -> 0
B15: TOTAL REVENUE | C15: ='P&L Model'!G12*C6 -> 6988.2353 | D15: ='P&L Model'!G12*D6 -> 5124.7059 | E15: ='P&L Model'!G12*E6 -> 4192.9412 | F15: ='P&L Model'!G12*F6 -> 2329.4118 | G15: ='P&L Model'!G12*G6 -> 1164.7059 | H15: =SUM(C15:G15) -> 19800 | I15: =H15-'P&L Model'!G12 -> 0
B16: II. COST ALLOCATION
B17: 2.1 Events & Activities | C17: ='P&L Model'!G15*C6 -> 847.05882 | D17: ='P&L Model'!G15*D6 -> 621.17647 | E17: ='P&L Model'!G15*E6 -> 508.23529 | F17: ='P&L Model'!G15*F6 -> 282.35294 | G17: ='P&L Model'!G15*G6 -> 141.17647 | H17: =SUM(C17:G17) -> 2400 | I17: =H17-'P&L Model'!G15 -> 0
B18: 2.2 Project Delivery Costs | C18: ='P&L Model'!G16*C6 -> 423.52941 | D18: ='P&L Model'!G16*D6 -> 310.58824 | E18: ='P&L Model'!G16*E6 -> 254.11765 | F18: ='P&L Model'!G16*F6 -> 141.17647 | G18: ='P&L Model'!G16*G6 -> 70.588235 | H18: =SUM(C18:G18) -> 1200 | I18: =H18-'P&L Model'!G16 -> 0
B19: 2.3 Travel & Client Meetings | C19: ='P&L Model'!G17*C6 -> 141.17647 | D19: ='P&L Model'!G17*D6 -> 103.52941 | E19: ='P&L Model'!G17*E6 -> 84.705882 | F19: ='P&L Model'!G17*F6 -> 47.058824 | G19: ='P&L Model'!G17*G6 -> 23.529412 | H19: =SUM(C19:G19) -> 400 | I19: =H19-'P&L Model'!G17 -> 0
B20: 2.4 Marketing & Communications | C20: ='P&L Model'!G18*C6 -> 169.41176 | D20: ='P&L Model'!G18*D6 -> 124.23529 | E20: ='P&L Model'!G18*E6 -> 101.64706 | F20: ='P&L Model'!G18*F6 -> 56.470588 | G20: ='P&L Model'!G18*G6 -> 28.235294 | H20: =SUM(C20:G20) -> 480 | I20: =H20-'P&L Model'!G18 -> 0
B21: 2.5 Software & Digital Tools | C21: ='P&L Model'!G19*C6 -> 84.705882 | D21: ='P&L Model'!G19*D6 -> 62.117647 | E21: ='P&L Model'!G19*E6 -> 50.823529 | F21: ='P&L Model'!G19*F6 -> 28.235294 | G21: ='P&L Model'!G19*G6 -> 14.117647 | H21: =SUM(C21:G21) -> 240 | I21: =H21-'P&L Model'!G19 -> 0
B22: 2.6 Admin & Miscellaneous | C22: ='P&L Model'!G20*C6 -> 56.470588 | D22: ='P&L Model'!G20*D6 -> 41.411765 | E22: ='P&L Model'!G20*E6 -> 33.882353 | F22: ='P&L Model'!G20*F6 -> 18.823529 | G22: ='P&L Model'!G20*G6 -> 9.4117647 | H22: =SUM(C22:G22) -> 160 | I22: =H22-'P&L Model'!G20 -> 0
B23: 2.7 Contingency Reserve | C23: ='P&L Model'!G21*C6 -> 137.78824 | D23: ='P&L Model'!G21*D6 -> 101.04471 | E23: ='P&L Model'!G21*E6 -> 82.672941 | F23: ='P&L Model'!G21*F6 -> 45.929412 | G23: ='P&L Model'!G21*G6 -> 22.964706 | H23: =SUM(C23:G23) -> 390.4 | I23: =H23-'P&L Model'!G21 -> 0
B24: TOTAL COSTS | C24: ='P&L Model'!G22*C6 -> 1860.1412 | D24: ='P&L Model'!G22*D6 -> 1364.1035 | E24: ='P&L Model'!G22*E6 -> 1116.0847 | F24: ='P&L Model'!G22*F6 -> 620.04706 | G24: ='P&L Model'!G22*G6 -> 310.02353 | H24: =SUM(C24:G24) -> 5270.4 | I24: =H24-'P&L Model'!G22 -> 0
B25: III. NET POSITION
B26: Net Surplus / (Deficit) (€) | C26: ='P&L Model'!G25*C6 -> 5128.0941 | D26: ='P&L Model'!G25*D6 -> 3760.6024 | E26: ='P&L Model'!G25*E6 -> 3076.8565 | F26: ='P&L Model'!G25*F6 -> 1709.3647 | G26: ='P&L Model'!G25*G6 -> 854.68235 | H26: =SUM(C26:G26) -> 14529.6 | I26: =H26-'P&L Model'!G25 -> 0
B28: Allocation basis: member headcount per campus (Paris 35%, Berlin 26%, London 21%, Madrid 12%, Turin 6%). The 'Verify' column should show €0 across all lines — any non-zero indicates a rounding or formula error. Adjust headcount inputs (row 5) to reflect actual campus membership each semester.
